zdpapi_router/__init__.py
zdpapi_router/crud.py
zdpapi_router/request_schema.py
zdpapi_router/response.py
zdpapi_router/response_schema.py
zdpapi_router/router.py
zdpapi_router-1.0.0.dist-info/LICENSE
zdpapi_router-1.0.0.dist-info/WHEEL
zdpapi_router-1.0.0.dist-info/METADATA
zdpapi_router-1.0.0.dist-info/RECORD
