Metadata-Version: 2.1
Name: zdpapi-router
Version: 1.0.0
Summary: 快速开发后端API的路由组件，支持自动生成CRUD接口
Home-page: https://github.com/zhangdapeng520/zdpapi_router
License: MIT
Keywords: zapi,router,crud,async,zhangdapeng
Author: 张大鹏
Author-email: lxgzhw@163.com
Requires-Python: >=3.8,<4.0
Classifier: License :: OSI Approved :: MIT License
Classifier: Programming Language :: Python :: 3
Classifier: Programming Language :: Python :: 3.8
Classifier: Programming Language :: Python :: 3.9
Requires-Dist: zdpapi (>=0.1.0,<0.2.0)
Requires-Dist: zdpapi-mysql (>=1.0.2,<2.0.0)
Project-URL: Documentation, https://github.com/zhangdapeng520/zdpapi_router
Project-URL: Repository, https://github.com/zhangdapeng520/zdpapi_router
